dstm/__init__.py
dstm/__main__.py
dstm/client/__init__.py
dstm/client/amqp.py
dstm/client/base.py
dstm/client/sqs.py
dstm/client/uri.py
dstm/exceptions.py
dstm/message.py
dstm/py.typed
dstm/tasks/__init__.py
dstm/tasks/broker.py
dstm/tasks/cli.py
dstm/tasks/task.py
dstm/tasks/types.py
dstm/tasks/wiring.py
dstm/tasks/worker.py
dstm-0.1.6.dist-info/WHEEL
dstm-0.1.6.dist-info/METADATA
dstm-0.1.6.dist-info/RECORD
